xoshiro/__init__.py
usainboltz-0.2.1.dist-info/WHEEL
usainboltz-0.2.1.dist-info/RECORD
usainboltz-0.2.1.dist-info/LICENSE.txt
usainboltz-0.2.1.dist-info/METADATA
usainboltz-0.2.1.dist-info/top_level.txt
usainboltz/oracle.py
usainboltz/simulator.cpython-38-x86_64-linux-gnu.so
usainboltz/__init__.py
usainboltz/generator.cpython-38-x86_64-linux-gnu.so
usainboltz/cpp_simulator.cpython-38-x86_64-linux-gnu.so
usainboltz/grammar.py
usainboltz/examples/mondrian.py
usainboltz/examples/__init__.py
usainboltz/examples/rna.py
usainboltz/examples/alcohols.py
usainboltz/examples/expnums.py
usainboltz/examples/knr19.py
usainboltz/examples/polya_trees.py
usainboltz/sage_examples/composition.py
usainboltz/sage_examples/__init__.py
usainboltz/sage_examples/cayley_tree.py
usainboltz/sage_examples/dyck_word.py
usainboltz/sage_examples/binary_tree.py
