Metadata-Version: 2.1
Name: usainboltz
Version: 0.2.1
Summary: Fast Boltzmann random generators for SageMath
Home-page: https://gitlab.com/ParComb/usain-boltz
Author: Matthieu Dien, Martin Pépin
Author-email: kerl@wkerl.me
License: GPLv3+
Project-URL: Bug Tracker, https://gitlab.com/ParComb/usain-boltz/issues
Project-URL: Documentation, https://usain-boltz.readthedocs.io
Project-URL: Source Code, https://gitlab.com/ParComb/usain-boltz
Classifier: Programming Language :: Python :: 3
Classifier: Programming Language :: Cython
Classifier: Programming Language :: C++
Classifier: License :: OSI Approved :: GNU General Public License v3 or later (GPLv3+)
Classifier: Operating System :: OS Independent
Requires-Python: >=3.7
License-File: LICENSE.txt
